{
  "courses": [
    {
      "id": "info_tech_2",
      "name": "情報技術II",
      "description": "プログラミング基礎とアルゴリズム",
      "icon": "fas fa-laptop-code",
      "folder": "information_technology_2"
    },
    {
      "id": "info_tech_3",
      "name": "情報技術III",
      "description": "データベースとWebアプリケーション",
      "icon": "fas fa-database",
      "folder": "information_technology_3"
    }
  ],
  "content": {
    "info_tech_2": [
      {
        "title": "第1回 講義資料",
        "type": "class",
        "url": "/info-tech-portal/information_technology_2/class1.html"
      },
      {
        "title": "第2回 講義資料",
        "type": "class",
        "url": "/info-tech-portal/information_technology_2/class2.html"
      }
    ],
    "info_tech_3": [
      {
        "title": "第1回 講義資料",
        "type": "class",
        "url": "/info-tech-portal/information_technology_3/class1.html"
      },
      {
        "title": "第2回 講義資料",
        "type": "class",
        "url": "/info-tech-portal/information_technology_3/class2.html"
      }
    ]
  },
  "links": [
    {
      "id": "id_1752121818963_cmplbyh7p",
      "title": "中間テスト(情報技術Ⅲ)",
      "url": "https://forms.gle/CnLoacBJw61ueJfVA",
      "description": "",
      "newTab": true,
      "order": 1,
      "courseId": "info_tech_3",
      "type": "class1",
      "createdAt": "2025-07-10T04:30:18.963Z"
    },
    {
      "id": "id_1752121839780_vz0n7o93t",
      "title": "中間テスト(情報技術Ⅲ)",
      "url": "https://forms.gle/PiDy3RmgnKfDZmVM9",
      "description": "",
      "newTab": true,
      "order": 1,
      "courseId": "info_tech_3",
      "type": "class2",
      "createdAt": "2025-07-10T04:30:39.780Z"
    },
    {
      "id": "id_1752121872028_oq832zvx8",
      "title": "情報技術II_中間テスト",
      "url": "https://forms.gle/PmDgVoJ4DJugAbzo6",
      "description": "",
      "newTab": true,
      "order": 1,
      "courseId": "info_tech_2",
      "type": "class1",
      "createdAt": "2025-07-10T04:31:12.028Z"
    },
    {
      "id": "id_1752121904150_xtazptqfm",
      "title": "情報技術II_中間テスト",
      "url": "https://forms.gle/g9uRnEXYbxAdo3fT8",
      "description": "",
      "newTab": true,
      "order": 1,
      "courseId": "info_tech_2",
      "type": "class2",
      "createdAt": "2025-07-10T04:31:44.150Z"
    }
  ]
}